lrng/__init__.py
lrng/lrng.py
lrng/settings.py
lrng/numba/__init__.py
lrng/numba/coalesce.py
lrng/numba/conversions.py
lrng/numba/labels.py
lrng/numba/pad.py
lrng/numpy/__init__.py
lrng/numpy/coalesce.py
lrng/numpy/conversions.py
lrng/numpy/labels.py
lrng/numpy/pad.py
lrng-1.0.1.dist-info/METADATA
lrng-1.0.1.dist-info/WHEEL
lrng-1.0.1.dist-info/top_level.txt
lrng-1.0.1.dist-info/RECORD
