Metadata-Version: 2.1
Name: lrng
Version: 1.0.1
Summary: Labeled Ranges
Home-page: https://gitlab.com/SumNeuron/lrng
Author: Sumner Magruder
Author-email: sumner.magruder@zmnh.uni-hamburg.de
License: UNKNOWN
Platform: UNKNOWN
Classifier: Programming Language :: Python :: 3.5
Classifier: License :: OSI Approved :: MIT License
Classifier: Operating System :: OS Independent
Requires-Dist: numba
Requires-Dist: numpy
